LICENSE
README.md
setup.py
rubikax/__init__.py
rubikax/rubx.py
rubikax.egg-info/PKG-INFO
rubikax.egg-info/SOURCES.txt
rubikax.egg-info/dependency_links.txt
rubikax.egg-info/requires.txt
rubikax.egg-info/top_level.txt