Metadata-Version: 2.1
Name: rubikax
Version: 1.0.0
Summary: [*] > a module or library for rubika messenger from iran ! rubika.ir/indentation
Home-page: https://github.com/mester-root/rubx
Download-URL: https://github.com/mester-root/rubx
Author: Saleh root
Author-email: creator.ryson@gmail.com
License: MIT
Keywords: rubx,rubix,rubikax,rubika,bot,robot,library,rubikalib,rubikalibrary,rubika.ir,web.rubika.ir,m.rubika.ir
Classifier: Development Status :: 3 - Alpha
Classifier: Intended Audience :: Developers
Classifier: Topic :: Software Development :: Build Tools
Classifier: License :: OSI Approved :: MIT License
Classifier: Programming Language :: Python :: 3
Classifier: Programming Language :: Python :: 3.4
Classifier: Programming Language :: Python :: 3.5
Classifier: Programming Language :: Python :: 3.6
Classifier: Programming Language :: Python :: 3.7
Classifier: Programming Language :: Python :: 3.8
Classifier: Programming Language :: Python :: 3.9
License-File: LICENSE
